localis/__init__.py
localis/data/cities/cities.tsv
localis/data/cities/cities_filter_index.tsv
localis/data/cities/cities_lookup_index.tsv
localis/data/cities/cities_search_index.tsv
localis/data/countries/countries.tsv
localis/data/countries/countries_filter_index.tsv
localis/data/countries/countries_lookup_index.tsv
localis/data/countries/countries_search_index.tsv
localis/data/subdivisions/subdivisions.tsv
localis/data/subdivisions/subdivisions_filter_index.tsv
localis/data/subdivisions/subdivisions_lookup_index.tsv
localis/data/subdivisions/subdivisions_search_index.tsv
localis/indexes/__init__.py
localis/indexes/filter_index.py
localis/indexes/index.py
localis/indexes/lookup_index.py
localis/indexes/search_index.py
localis/models/__init__.py
localis/models/city.py
localis/models/country.py
localis/models/model.py
localis/models/subdivision.py
localis/registries/__init__.py
localis/registries/city_registry.py
localis/registries/country_registry.py
localis/registries/registry.py
localis/registries/subdivision_registry.py
localis/utils.py
localis-1.0.0a3.dist-info/METADATA
localis-1.0.0a3.dist-info/WHEEL
localis-1.0.0a3.dist-info/entry_points.txt
localis-1.0.0a3.dist-info/licenses/LICENSE
localis-1.0.0a3.dist-info/RECORD
