Metadata-Version: 2.4
Name: localis
Version: 1.0.0a3
Summary: Fast, offline access to comprehensive data for countries, subdivisions, and cities. Built on ISO 3166 and GeoNames datasets with support for exact lookups, filtering, and fuzzy search.
License-Expression: MIT
License-File: LICENSE
Keywords: country,subdivision,city,iso,3166,3166-1,3166-2,geonames
Author: danimal
Author-email: dan.stoffels@gmail.com
Requires-Python: >=3.11
Classifier: Development Status :: 3 - Alpha
Classifier: Intended Audience :: Developers
Classifier: License :: OSI Approved :: MIT License
Classifier: Programming Language :: Python :: 3
Classifier: Programming Language :: Python :: 3.11
Classifier: Programming Language :: Python :: 3.12
Classifier: Topic :: Software Development :: Libraries :: Python Modules
Classifier: Topic :: Scientific/Engineering :: GIS
Requires-Dist: rapidfuzz (>=3.13.0)
Requires-Dist: unidecode (>=1.4.0)
Project-URL: Homepage, https://pypi.org/project/localis/
Project-URL: Repository, https://github.com/dstoffels/localis
